webflow/__init__.py
webflow/client.py
webflow/core/__init__.py
webflow/core/api_error.py
webflow/core/client_wrapper.py
webflow/core/datetime_utils.py
webflow/core/file.py
webflow/core/jsonable_encoder.py
webflow/core/remove_none_from_dict.py
webflow/core/request_options.py
webflow/environment.py
webflow/errors/__init__.py
webflow/errors/bad_request_error.py
webflow/errors/conflict_error.py
webflow/errors/forbidden_error.py
webflow/errors/internal_server_error.py
webflow/errors/not_found_error.py
webflow/errors/too_many_requests_error.py
webflow/errors/unauthorized_error.py
webflow/oauth.py
webflow/py.typed
webflow/resources/__init__.py
webflow/resources/access_groups/__init__.py
webflow/resources/access_groups/client.py
webflow/resources/access_groups/types/__init__.py
webflow/resources/access_groups/types/access_groups_list_request_sort.py
webflow/resources/assets/__init__.py
webflow/resources/assets/client.py
webflow/resources/collections/__init__.py
webflow/resources/collections/client.py
webflow/resources/collections/resources/__init__.py
webflow/resources/collections/resources/fields/__init__.py
webflow/resources/collections/resources/fields/client.py
webflow/resources/collections/resources/fields/types/__init__.py
webflow/resources/collections/resources/fields/types/field_create_type.py
webflow/resources/collections/resources/items/__init__.py
webflow/resources/collections/resources/items/client.py
webflow/resources/collections/resources/items/types/__init__.py
webflow/resources/collections/resources/items/types/bulk_collection_item_field_data.py
webflow/resources/collections/resources/items/types/items_publish_item_response.py
webflow/resources/ecommerce/__init__.py
webflow/resources/ecommerce/client.py
webflow/resources/forms/__init__.py
webflow/resources/forms/client.py
webflow/resources/inventory/__init__.py
webflow/resources/inventory/client.py
webflow/resources/inventory/types/__init__.py
webflow-1.1.0.dist-info/METADATA
webflow-1.1.0.dist-info/WHEEL
webflow-1.1.0.dist-info/RECORD
